tests/__init__.py
tests/geosearch_test.py
tests/lang_test.py
tests/page_test.py
tests/request_mock_data.py
tests/search_test.py
wikipedia_zh/__init__.py
wikipedia_zh/exceptions.py
wikipedia_zh/util.py
wikipedia_zh/wikipedia.py
wikipedia_zh-0.0.6.dist-info/METADATA
wikipedia_zh-0.0.6.dist-info/WHEEL
wikipedia_zh-0.0.6.dist-info/top_level.txt
wikipedia_zh-0.0.6.dist-info/RECORD
