Metadata-Version: 2.1
Name: wikipedia-zh
Version: 0.0.6
Summary: Wikipedia Zh API for Python
Home-page: https://gitee.com/zh19990906/wikipedia_zh
Author: Heng Zhang
Author-email: 1093869292@qq.com
License: UNKNOWN
Platform: UNKNOWN
Classifier: Programming Language :: Python :: 3
Classifier: License :: OSI Approved :: MIT License
Classifier: Operating System :: OS Independent
Requires-Dist: beautifulsoup4
Requires-Dist: requests (<3.0.0,>=2.0.0)
